tensorio/__init__.py
tensorio/command_line_interface.py
tensorio/cli/__init__.py
tensorio/cli/bundle/__init__.py
tensorio/cli/bundle/arg_parser.py
tensorio/cli/bundle/executor.py
tensorio/cli/convert/__init__.py
tensorio/cli/convert/arg_parser.py
tensorio/cli/convert/executor.py
tensorio/cli/utils/__init__.py
tensorio/cli/utils/exceptions.py
tensorio/convert/__init__.py
tensorio/convert/tensorflow.py
tensorio/model_bundle/__init__.py
tensorio/model_bundle/bundler.py
tensorio-0.1.1.dist-info/LICENSE
tensorio-0.1.1.dist-info/METADATA
tensorio-0.1.1.dist-info/WHEEL
tensorio-0.1.1.dist-info/entry_points.txt
tensorio-0.1.1.dist-info/top_level.txt
tensorio-0.1.1.dist-info/RECORD
